LICENSE.md
MANIFEST.in
README.md
pyproject.toml
torchpathdiffeq/__init__.py
torchpathdiffeq/base.py
torchpathdiffeq/distributed.py
torchpathdiffeq/examples.py
torchpathdiffeq/methods.py
torchpathdiffeq/parallel_solver.py
torchpathdiffeq/path_integral.py
torchpathdiffeq/runge_kutta.py
torchpathdiffeq/serial_solver.py
torchpathdiffeq.egg-info/PKG-INFO
torchpathdiffeq.egg-info/SOURCES.txt
torchpathdiffeq.egg-info/dependency_links.txt
torchpathdiffeq.egg-info/requires.txt
torchpathdiffeq.egg-info/top_level.txt